Workbook

Sheet Final
A1: Ticket # | B1: Company | C1: Type | D1: Issue Description | E1: Solution | F1: Issue Type | G1: Related Project | H1: Related Sub-Module | I1: Issue Priority | J1: Raised By Code | K1: Raised By Name | L1: Department | M1: Assigned To | N1: Stard Date | O1: End Date | P1: No. of day | Q1: Issue Status | R1: Remark
A2: =IF(C2<>"",ROW(A1),"") -> 1 | C2: Development | D2: Created Login and CreateAccount pages for users | F2: Web | G2: HRinitialData | I2: Meduim | J2: 9 | K2: =IF(J2<>"",VLOOKUP(J2,HeadCount!A:I,2,0),"") -> Nassereldin Mohamed Salaheldin Nasreldin | L2: =IF(J2<>"",VLOOKUP(J2,HeadCount!A:I,5,0),"") -> IT | N2: 45860 | O2: 45860 | P2: =IF(N2="","",(O2-N2)+1) -> 1 | Q2: Resolved
A3: =IF(C3<>"",ROW(A2),"") -> 2 | C3: Development | D3: Created Employees,Positions,Company,Product,Department screens | F3: Web | G3: HRinitialData | I3: Meduim | J3: 9 | K3: =IF(J3<>"",VLOOKUP(J3,HeadCount!A:I,2,0),"") -> Nassereldin Mohamed Salaheldin Nasreldin | L3: =IF(J3<>"",VLOOKUP(J3,HeadCount!A:I,5,0),"") -> IT | N3: 45860 | O3: 45860 | P3: =IF(N3="","",(O3-N3)+1) -> 1 | Q3: Resolved
A4: =IF(C4<>"",ROW(A3),"") -> 3 | C4: Development | D4: Added tables to provide history, the ability to delete and edit | F4: Web | G4: HRinitialData | I4: Meduim | J4: 9 | K4: =IF(J4<>"",VLOOKUP(J4,HeadCount!A:I,2,0),"") -> Nassereldin Mohamed Salaheldin Nasreldin | L4: =IF(J4<>"",VLOOKUP(J4,HeadCount!A:I,5,0),"") -> IT | N4: 45861 | O4: 45861 | P4: =IF(N4="","",(O4-N4)+1) -> 1 | Q4: Resolved
A5: =IF(C5<>"",ROW(A4),"") -> 4 | C5: Study | D5: Studyigng zenhr system to know more about its implementation | F5: Web | G5: HRinitialData | I5: Meduim | J5: 9 | K5: =IF(J5<>"",VLOOKUP(J5,HeadCount!A:I,2,0),"") -> Nassereldin Mohamed Salaheldin Nasreldin | L5: =IF(J5<>"",VLOOKUP(J5,HeadCount!A:I,5,0),"") -> IT | N5: 45865 | O5: 45865 | P5: =IF(N5="","",(O5-N5)+1) -> 1 | Q5: In Progress
A6: =IF(C6<>"",ROW(A5),"") -> 5 | C6: Study | D6: studying more about the zenhr system and implementation and screens | F6: Web | G6: HRinitialData | I6: Meduim | J6: 9 | K6: =IF(J6<>"",VLOOKUP(J6,HeadCount!A:I,2,0),"") -> Nassereldin Mohamed Salaheldin Nasreldin | L6: =IF(J6<>"",VLOOKUP(J6,HeadCount!A:I,5,0),"") -> IT | N6: 45866 | O6: 45866 | P6: =IF(N6="","",(O6-N6)+1) -> 1 | Q6: Resolved
A7: =IF(C7<>"",ROW(A6),"") -> 6 | C7: Development | D7: making a part of the employee screens and creating employee | F7: Web | G7: HRinitialData | I7: Meduim | J7: 9 | K7: =IF(J7<>"",VLOOKUP(J7,HeadCount!A:I,2,0),"") -> Nassereldin Mohamed Salaheldin Nasreldin | L7: =IF(J7<>"",VLOOKUP(J7,HeadCount!A:I,5,0),"") -> IT | N7: 45867 | O7: 45867 | P7: =IF(N7="","",(O7-N7)+1) -> 1 | Q7: In Progress
A8: =IF(C8<>"",ROW(A7),"") -> 7 | C8: Development | D8: Finshing the employee screens with creations and assets | F8: web | G8: HRinitialData | I8: Meduim | J8: 9 | K8: =IF(J8<>"",VLOOKUP(J8,HeadCount!A:I,2,0),"") -> Nassereldin Mohamed Salaheldin Nasreldin | L8: =IF(J8<>"",VLOOKUP(J8,HeadCount!A:I,5,0),"") -> IT | N8: 45868 | O8: 45868 | P8: =IF(N8="","",(O8-N8)+1) -> 1 | Q8: Resolved
A9: =IF(C9<>"",ROW(A8),"") -> 8 | C9: Development | D9: making part of documents and applying for vacations | F9: web | G9: HRinitialData | I9: Meduim | J9: 9 | K9: =IF(J9<>"",VLOOKUP(J9,HeadCount!A:I,2,0),"") -> Nassereldin Mohamed Salaheldin Nasreldin | L9: =IF(J9<>"",VLOOKUP(J9,HeadCount!A:I,5,0),"") -> IT | N9: 45869 | O9: 45869 | P9: =IF(N9="","",(O9-N9)+1) -> 1 | Q9: In Progress
A10: =IF(C10<>"",ROW(A9),"") -> 9 | C10: Development | D10: Backend system for task based system for finishers | F10: Web | G10: TasksBasedSystem | I10: Meduim | J10: 245 | K10: =IF(J10<>"",VLOOKUP(J10,HeadCount!A:I,2,0),"") -> Mohmed Khairy Elgendy Mohamed AboAmmer | L10: =IF(J10<>"",VLOOKUP(J10,HeadCount!A:I,5,0),"") -> R&D | N10: 45872 | O10: 45873 | P10: =IF(N10="","",(O10-N10)+1) -> 2 | Q10: Resolved
A11: =IF(C11<>"",ROW(A10),"") -> 10 | C11: Development | D11: some of the frontend for the task based system | F11: web | G11: TasksBasedSystem | I11: Meduim | J11: 245 | K11: =IF(J11<>"",VLOOKUP(J11,HeadCount!A:I,2,0),"") -> Mohmed Khairy Elgendy Mohamed AboAmmer | L11: =IF(J11<>"",VLOOKUP(J11,HeadCount!A:I,5,0),"") -> R&D | N11: 45873 | O11: 45874 | P11: =IF(N11="","",(O11-N11)+1) -> 2 | Q11: Resolved
A12: =IF(C12<>"",ROW(A11),"") -> 11 | C12: Development | D12: enhancing frontend, allowing platform for different users and roles, integration with access | F12: web | G12: TasksBasedSystem | I12: Meduim | J12: 245 | K12: =IF(J12<>"",VLOOKUP(J12,HeadCount!A:I,2,0),"") -> Mohmed Khairy Elgendy Mohamed AboAmmer | L12: =IF(J12<>"",VLOOKUP(J12,HeadCount!A:I,5,0),"") -> R&D | N12: 45874 | O12: 45874 | P12: =IF(N12="","",(O12-N12)+1) -> 1 | Q12: Resolved
A13: =IF(C13<>"",ROW(A12),"") -> 12 | C13: Development | D13: using scheduler and allowing tables to be nullable for admins and working with mods, comments backend | F13: Web | G13: TasksBasedSystem | I13: Meduim | J13: 245 | K13: =IF(J13<>"",VLOOKUP(J13,HeadCount!A:I,2,0),"") -> Mohmed Khairy Elgendy Mohamed AboAmmer | L13: =IF(J13<>"",VLOOKUP(J13,HeadCount!A:I,5,0),"") -> R&D | N13: 45875 | O13: 45875 | P13: =IF(N13="","",(O13-N13)+1) -> 1 | Q13: Resolved
... A17: =IF(C17<>"",ROW(A16),"") -> 16 | C17: Development | D17: subrequest approval table and actions based on previous state, max size handling, fixing emails | F17: Web | G17: TasksBasedSystem | I17: Meduim | J17: 245 | K17: =IF(J17<>"",VLOOKUP(J17,HeadCount!A:I,2,0),"") -> Mohmed Khairy Elgendy Mohamed AboAmmer | L17: =IF(J17<>"",VLOOKUP(J17,HeadCount!A:I,5,0),"") -> R&D | N17: 45881 | O17: 45881 | P17: =IF(N17="","",(O17-N17)+1) -> 1 | Q17: Resolved
A18: =IF(C18<>"",ROW(A17),"") -> 17 | C18: Development | D18: subrequest approval frontend and its differnet situations and soft deletion of everything | F18: web | G18: TasksBasedSystem | I18: Meduim | J18: 245 | K18: =IF(J18<>"",VLOOKUP(J18,HeadCount!A:I,2,0),"") -> Mohmed Khairy Elgendy Mohamed AboAmmer | L18: =L20 -> R&D | N18: 45882 | O18: 45882 | P18: =IF(N18="","",(O18-N18)+1) -> 1 | Q18: Resolved
A19: =IF(C19<>"",ROW(A18),"") -> 18 | C19: Development | D19: notifications and email sending and being late notices, | F19: web | G19: TasksBasedSystem | I19: Meduim | J19: 245 | K19: =IF(J19<>"",VLOOKUP(J19,HeadCount!A:I,2,0),"") -> Mohmed Khairy Elgendy Mohamed AboAmmer | L19: =IF(J19<>"",VLOOKUP(J19,HeadCount!A:I,5,0),"") -> R&D | N19: 45883 | O19: 45883 | P19: =IF(N19="","",(O19-N19)+1) -> 1 | Q19: Resolved
A20: =IF(C20<>"",ROW(A19),"") -> 19 | C20: Development | D20: Fixing the edit request and subrequest buttons not working, setting up application to work in the remote server, uploading emails from excel | F20: web | G20: TasksBasedSystem | I20: Meduim | J20: 245 | K20: =IF(J20<>"",VLOOKUP(J20,HeadCount!A:I,2,0),"") -> Mohmed Khairy Elgendy Mohamed AboAmmer | L20: =IF(J20<>"",VLOOKUP(J20,HeadCount!A:I,5,0),"") -> R&D | N20: 45886 | O20: 45886 | P20: =IF(N20="","",(O20-N20)+1) -> 1 | Q20: Resolved
A21: =IF(C21<>"",ROW(A20),"") -> 20 | C21: Development | D21: testing and debugging code, fixing not showing elements, approval request notification and project summary, half publishing | F21: web | G21: TasksBasedSystem | I21: Meduim | J21: 245 | K21: =IF(J21<>"",VLOOKUP(J21,HeadCount!A:I,2,0),"") -> Mohmed Khairy Elgendy Mohamed AboAmmer | L21: =IF(J21<>"",VLOOKUP(J21,HeadCount!A:I,5,0),"") -> R&D | N21: 45887 | O21: 45887 | P21: =IF(N21="","",(O21-N21)+1) -> 1 | Q21: Resolved
A22: =IF(C22<>"",ROW(A21),"") -> 21 | C22: Development | D22: trying to publish and fix publish issue, uploading employee button | F22: web | G22: TasksBasedSystem | I22: Meduim | J22: 245 | K22: =IF(J22<>"",VLOOKUP(J22,HeadCount!A:I,2,0),"") -> Mohmed Khairy Elgendy Mohamed AboAmmer | L22: =IF(J22<>"",VLOOKUP(J22,HeadCount!A:I,5,0),"") -> R&D | N22: 45888 | O22: 45888 | P22: =IF(N22="","",(O22-N22)+1) -> 1 | Q22: Resolved
A23: =IF(C23<>"",ROW(A22),"") -> 22 | C23: Development | D23: finishing publish and trying to solve publish issues, design improvements | F23: web | G23: TasksBasedSystem | I23: Meduim | J23: 245 | K23: =IF(J23<>"",VLOOKUP(J23,HeadCount!A:I,2,0),"") -> Mohmed Khairy Elgendy Mohamed AboAmmer | L23: =IF(J23<>"",VLOOKUP(J23,HeadCount!A:I,5,0),"") -> R&D | N23: 45889 | O23: 45889 | P23: =IF(N23="","",(O23-N23)+1) -> 1 | Q23: Resolved
A24: =IF(C24<>"",ROW(A23),"") -> 23 | C24: Development | D24: Fixing the put and delete not working due to cors, fixing the scheduler, finalizing project | F24: web | G24: TasksBasedSystem | I24: Meduim | J24: 245 | K24: =IF(J24<>"",VLOOKUP(J24,HeadCount!A:I,2,0),"") -> Mohmed Khairy Elgendy Mohamed AboAmmer | L24: =IF(J24<>"",VLOOKUP(J24,HeadCount!A:I,5,0),"") -> R&D | N24: 45890 | O24: 45890 | P24: =IF(N24="","",(O24-N24)+1) -> 1 | Q24: Resolved
A25: =IF(C25<>"",ROW(A24),"") | K25: =IF(J25<>"",VLOOKUP(J25,HeadCount!A:I,2,0),"") | L25: =IF(J25<>"",VLOOKUP(J25,HeadCount!A:I,5,0),"") | P25: =IF(N25="","",(O25-N25)+1)
A26: =IF(C26<>"",ROW(A25),"") | K26: =IF(J26<>"",VLOOKUP(J26,HeadCount!A:I,2,0),"") | L26: =IF(J26<>"",VLOOKUP(J26,HeadCount!A:I,5,0),"") | P26: =IF(N26="","",(O26-N26)+1)
A27: =IF(C27<>"",ROW(A26),"") | K27: =IF(J27<>"",VLOOKUP(J27,HeadCount!A:I,2,0),"") | L27: =IF(J27<>"",VLOOKUP(J27,HeadCount!A:I,5,0),"") | P27: =IF(N27="","",(O27-N27)+1)
A28: =IF(C28<>"",ROW(A27),"") | K28: =IF(J28<>"",VLOOKUP(J28,HeadCount!A:I,2,0),"") | L28: =IF(J28<>"",VLOOKUP(J28,HeadCount!A:I,5,0),"") | P28: =IF(N28="","",(O28-N28)+1)
A29: =IF(C29<>"",ROW(A28),"") | K29: =IF(J29<>"",VLOOKUP(J29,HeadCount!A:I,2,0),"") | L29: =IF(J29<>"",VLOOKUP(J29,HeadCount!A:I,5,0),"") | P29: =IF(N29="","",(O29-N29)+1)
A30: =IF(C30<>"",ROW(A29),"") | K30: =IF(J30<>"",VLOOKUP(J30,HeadCount!A:I,2,0),"") | L30: =IF(J30<>"",VLOOKUP(J30,HeadCount!A:I,5,0),"") | P30: =IF(N30="","",(O30-N30)+1)
A31: =IF(C31<>"",ROW(A30),"") | K31: =IF(J31<>"",VLOOKUP(J31,HeadCount!A:I,2,0),"") | L31: =IF(J31<>"",VLOOKUP(J31,HeadCount!A:I,5,0),"") | P31: =IF(N31="","",(O31-N31)+1)
A32: =IF(C32<>"",ROW(A31),"") | K32: =IF(J32<>"",VLOOKUP(J32,HeadCount!A:I,2,0),"") | L32: =IF(J32<>"",VLOOKUP(J32,HeadCount!A:I,5,0),"") | P32: =IF(N32="","",(O32-N32)+1)
A33: =IF(C33<>"",ROW(A32),"") | K33: =IF(J33<>"",VLOOKUP(J33,HeadCount!A:I,2,0),"") | L33: =IF(J33<>"",VLOOKUP(J33,HeadCount!A:I,5,0),"") | P33: =IF(N33="","",(O33-N33)+1)
A34: =IF(C34<>"",ROW(A33),"") | K34: =IF(J34<>"",VLOOKUP(J34,HeadCount!A:I,2,0),"") | L34: =IF(J34<>"",VLOOKUP(J34,HeadCount!A:I,5,0),"") | P34: =IF(N34="","",(O34-N34)+1)
A35: =IF(C35<>"",ROW(A34),"") | K35: =IF(J35<>"",VLOOKUP(J35,HeadCount!A:I,2,0),"") | L35: =IF(J35<>"",VLOOKUP(J35,HeadCount!A:I,5,0),"") | P35: =IF(N35="","",(O35-N35)+1)
A36: =IF(C36<>"",ROW(A35),"") | K36: =IF(J36<>"",VLOOKUP(J36,HeadCount!A:I,2,0),"") | L36: =IF(J36<>"",VLOOKUP(J36,HeadCount!A:I,5,0),"") | P36: =IF(N36="","",(O36-N36)+1)
... A350: =IF(C350<>"",ROW(A349),"") | K350: =IF(J350<>"",VLOOKUP(J350,HeadCount!A:I,2,0),"") | L350: =IF(J350<>"",VLOOKUP(J350,HeadCount!A:I,5,0),"") | P350: =IF(N350="","",(O350-N350)+1)
A351: =IF(C351<>"",ROW(A350),"")
A352: =IF(C352<>"",ROW(A351),"")
A353: =IF(C353<>"",ROW(A352),"")
A354: =IF(C354<>"",ROW(A353),"")
A355: =IF(C355<>"",ROW(A354),"")
A356: =IF(C356<>"",ROW(A355),"")
A357: =IF(C357<>"",ROW(A356),"")
A358: =IF(C358<>"",ROW(A357),"")
A359: =IF(C359<>"",ROW(A358),"") | K359: =IF(J359<>"",VLOOKUP(J359,HeadCount!A:I,2,0),"") | L359: =IF(J359<>"",VLOOKUP(J359,HeadCount!A:I,5,0),"") | P359: =IF(N359="","",(O359-N359)+1)
A360: =IF(C360<>"",ROW(A359),"") | K360: =IF(J360<>"",VLOOKUP(J360,HeadCount!A:I,2,0),"") | L360: =IF(J360<>"",VLOOKUP(J360,HeadCount!A:I,5,0),"") | P360: =IF(N360="","",(O360-N360)+1)
A361: =IF(C361<>"",ROW(A360),"") | K361: =IF(J361<>"",VLOOKUP(J361,HeadCount!A:I,2,0),"") | L361: =IF(J361<>"",VLOOKUP(J361,HeadCount!A:I,5,0),"") | P361: =IF(N361="","",(O361-N361)+1)
A362: =IF(C362<>"",ROW(A361),"") | K362: =IF(J362<>"",VLOOKUP(J362,HeadCount!A:I,2,0),"") | L362: =IF(J362<>"",VLOOKUP(J362,HeadCount!A:I,5,0),"") | P362: =IF(N362="","",(O362-N362)+1)
A363: =IF(C363<>"",ROW(A362),"") | K363: =IF(J363<>"",VLOOKUP(J363,HeadCount!A:I,2,0),"") | L363: =IF(J363<>"",VLOOKUP(J363,HeadCount!A:I,5,0),"") | P363: =IF(N363="","",(O363-N363)+1)
A364: =IF(C364<>"",ROW(A363),"") | K364: =IF(J364<>"",VLOOKUP(J364,HeadCount!A:I,2,0),"") | L364: =IF(J364<>"",VLOOKUP(J364,HeadCount!A:I,5,0),"") | P364: =IF(N364="","",(O364-N364)+1)
A365: =IF(C365<>"",ROW(A364),"") | K365: =IF(J365<>"",VLOOKUP(J365,HeadCount!A:I,2,0),"") | L365: =IF(J365<>"",VLOOKUP(J365,HeadCount!A:I,5,0),"") | P365: =IF(N365="","",(O365-N365)+1)
A366: =IF(C366<>"",ROW(A365),"") | K366: =IF(J366<>"",VLOOKUP(J366,HeadCount!A:I,2,0),"") | L366: =IF(J366<>"",VLOOKUP(J366,HeadCount!A:I,5,0),"") | P366: =IF(N366="","",(O366-N366)+1)
A367: =IF(C367<>"",ROW(A366),"") | K367: =IF(J367<>"",VLOOKUP(J367,HeadCount!A:I,2,0),"") | L367: =IF(J367<>"",VLOOKUP(J367,HeadCount!A:I,5,0),"") | P367: =IF(N367="","",(O367-N367)+1)
A368: =IF(C368<>"",ROW(A367),"") | K368: =IF(J368<>"",VLOOKUP(J368,HeadCount!A:I,2,0),"") | L368: =IF(J368<>"",VLOOKUP(J368,HeadCount!A:I,5,0),"") | P368: =IF(N368="","",(O368-N368)+1)
A369: =IF(C369<>"",ROW(A368),"") | K369: =IF(J369<>"",VLOOKUP(J369,HeadCount!A:I,2,0),"") | L369: =IF(J369<>"",VLOOKUP(J369,HeadCount!A:I,5,0),"") | P369: =IF(N369="","",(O369-N369)+1)
A370: =IF(C370<>"",ROW(A369),"") | K370: =IF(J370<>"",VLOOKUP(J370,HeadCount!A:I,2,0),"") | L370: =IF(J370<>"",VLOOKUP(J370,HeadCount!A:I,5,0),"") | P370: =IF(N370="","",(O370-N370)+1)
... A1518: =IF(C1518<>"",ROW(A1517),"") | K1518: =IF(J1518<>"",VLOOKUP(J1518,HeadCount!A:I,2,0),"") | L1518: =IF(J1518<>"",VLOOKUP(J1518,HeadCount!A:I,5,0),"") | P1518: =IF(N1518="","",(O1518-N1518)+1)
A1519: =IF(C1519<>"",ROW(A1518),"") | L1519: =IF(J1519<>"",VLOOKUP(J1519,HeadCount!A:I,5,0),"") | P1519: =IF(N1519="","",(O1519-N1519)+1)
A1520: =IF(C1520<>"",ROW(A1519),"") | L1520: =IF(J1520<>"",VLOOKUP(J1520,HeadCount!A:I,5,0),"") | P1520: =IF(N1520="","",(O1520-N1520)+1)
A1521: =IF(C1521<>"",ROW(A1520),"") | L1521: =IF(J1521<>"",VLOOKUP(J1521,HeadCount!A:I,5,0),"") | P1521: =IF(N1521="","",(O1521-N1521)+1)
A1522: =IF(C1522<>"",ROW(A1521),"") | L1522: =IF(J1522<>"",VLOOKUP(J1522,HeadCount!A:I,5,0),"") | P1522: =IF(N1522="","",(O1522-N1522)+1)
A1523: =IF(C1523<>"",ROW(A1522),"") | L1523: =IF(J1523<>"",VLOOKUP(J1523,HeadCount!A:I,5,0),"") | P1523: =IF(N1523="","",(O1523-N1523)+1)
A1524: =IF(C1524<>"",ROW(A1523),"") | L1524: =IF(J1524<>"",VLOOKUP(J1524,HeadCount!A:I,5,0),"") | P1524: =IF(N1524="","",(O1524-N1524)+1)
A1525: =IF(C1525<>"",ROW(A1524),"") | L1525: =IF(J1525<>"",VLOOKUP(J1525,HeadCount!A:I,5,0),"") | P1525: =IF(N1525="","",(O1525-N1525)+1)
A1526: =IF(C1526<>"",ROW(A1525),"") | L1526: =IF(J1526<>"",VLOOKUP(J1526,HeadCount!A:I,5,0),"") | P1526: =IF(N1526="","",(O1526-N1526)+1)
A1527: =IF(C1527<>"",ROW(A1526),"") | L1527: =IF(J1527<>"",VLOOKUP(J1527,HeadCount!A:I,5,0),"") | P1527: =IF(N1527="","",(O1527-N1527)+1)
A1528: =IF(C1528<>"",ROW(A1527),"") | L1528: =IF(J1528<>"",VLOOKUP(J1528,HeadCount!A:I,5,0),"") | P1528: =IF(N1528="","",(O1528-N1528)+1)
A1529: =IF(C1529<>"",ROW(A1528),"") | L1529: =IF(J1529<>"",VLOOKUP(J1529,HeadCount!A:I,5,0),"") | P1529: =IF(N1529="","",(O1529-N1529)+1)
A1530: =IF(C1530<>"",ROW(A1529),"") | L1530: =IF(J1530<>"",VLOOKUP(J1530,HeadCount!A:I,5,0),"") | P1530: =IF(N1530="","",(O1530-N1530)+1)
... A3203: =IF(C3203<>"",ROW(A3202),"") | L3203: =IF(J3203<>"",VLOOKUP(J3203,HeadCount!A:I,5,0),"") | P3203: =IF(N3203="","",(O3203-N3203)+1)
P3204: =IF(N3204="","",(O3204-N3204)+1)

Sheet Values List
A1: Type | B1: Related Project | C1: Year Created | D1: Related Sub-Module | E1: Issue Priority | F1: Raised By | G1: Department | H1: Assigned To | I1: Issue Status | J1: Type | K1: Company
A2: Web | B2: Factory System | C2: 2021 | D2: Security & Transprotion & Break | E2: Critical | F2: Ahmed Ali | G2: IT Department | I2: New | J2: Study | K2: FPI
A3: JDE | B3: Hardware | C3: 2020 | E3: High | F3: Nasser Salah Nasr | G3: IT Department | I3: In Progress | J3: Troubleshooting | K3: Future Pro
B4: Fixed Assets | C4: 2020 | E4: Meduim | F4: Haitham Salah | G4: Admin | I4: On Hold | J4: Development | K4: Group
B5: IPC System | C5: 2022 | E5: Low | F5: Rasha Ayman | G5: Quality Assurance | I5: Resolved | J5: Meeting
B6: Clinic | C6: 2022 | F6: Mohamed Abdelghany | G6: Quality Assurance | I6: Cancelled | J6: Implementation
B7: Generate Character System | C7: 2022 | F7: Khaled Ahmed | G7: IT Department | I7: Failured | J7: Training
B8: FPI Cosmetics | C8: 2022
B9: Movements (FIN) | C9: 2022
B10: Pharmaceutical Chamber | C10: 2023
B11: Employee Mangement | C11: 2023
B12: Ref. Std. Solution | C12: 2023 & 2024
B13: Daily Attendance | C13: 2023
B14: CRM Data | C14: 2023
B15: CAPA | C15: 2023
B16: Files Attached | C16: 2023 & 2025
B17: R5531418S
B18: R550911V
B19: R5541550H
B20: Product Status
B21: R5531415F
B22: R5548001WO
B23: R5543500
B24: R554100QRN
B25: R554100RLS
B26: R5541H005
B27: R55040003
B28: R5542001H
... B52: TasksBasedSystem

Sheet HeadCount
A1: Code | B1: Name En | C1: Name Ar | D1: Position | E1: Department | F1: Resignation | G1: Resignation Name | H1: Email Address | I1: Type
A2: 1 | B2: Gamaleldin Ellithy | C2: جمال الدين الليثى | D2: CEO | E2: CEO | F2: 0 | G2: داخل الخدمة | H2: gleithy@future-eg.com | I2: Scientific Office
A3: 6 | B3: Marwa Ahmed Mohamed Sultan | C3: مروة احمد محمد سلطان | D3: Executive Officer Manager | E3: Admin | F3: 0 | G3: داخل الخدمة
A4: 8 | B4: Mohamed Mohamed Ahmed Abdelgawad Afifi | C4: محمد محمد احمد عبد الجواد عفيفى | D4: Financial Manager | E4: Finance | F4: 0 | G4: داخل الخدمة
A5: 9 | B5: Nassereldin Mohamed Salaheldin Nasreldin | C5: ناصر الدين محمد صلاح الدين نصر الدين الليثى | D5: IT Manager | E5: IT | F5: 0 | G5: داخل الخدمة
A6: 11 | B6: Heba Kamel AbdelSamad Kamel | C6: هبة كامل عبد الصمد كامل | D6: QA System & Training Manager | E6: Quality Assurance | F6: 0 | G6: داخل الخدمة | H6: h.kamel@future-eg.com
A7: 13 | B7: Osama Mohamed Elsayed Allam | C7: أسامه محمد السيد علام | D7: Quality Consultant | E7: Plant Management | F7: 0 | G7: داخل الخدمة
A8: 14 | B8: Ahmed Rafaat AbdelRahman Ali | C8: أحمد رافت عبد الرحمن علي | D8: Validation Manager | E8: Quality Assurance | F8: 0 | G8: داخل الخدمة | H8: a.raafat@future-eg.com
A9: 16 | B9: Waleed AbdelMonem Mansour Mohamed | C9: وليد عبد المنعم منصور محمد | D9: Blistering Operator Technician | E9: Production | F9: 0 | G9: داخل الخدمة
A10: 17 | B10: Mohamed Sobhy AbdelMonem Afify | C10: محمد صبحى عبد المنعم عفيفى | D10: Solid General Supervisor | E10: Production | F10: 0 | G10: داخل الخدمة
A11: 18 | B11: Reda Salah Saleh Farah | C11: رضا صلاح صالح فرح صالح | D11: Technician | E11: Engineering | F11: 0 | G11: داخل الخدمة
A12: 24 | B12: Abdullah Ibrahim Mohamed Ibrahim | C12: عبد الله ابراهيم محمد ابراهيم | D12: Admin & Financial Representative | E12: Transportation | F12: 0 | G12: داخل الخدمة | I12: Factory
A13: 27 | B13: Amr Mohamed AbdelBakie EID | C13: عمرو محمد عبد الباقى عيد | D13: Administration Supervisor | E13: Transportation | F13: 0 | G13: داخل الخدمة | I13: Factory
A14: 29 | B14: Ahmed Shafai Ali Mohamed | C14: احمد شافعى على محمد | D14: Distribution Representatives' Supervisor | E14: Warehouse Finished Product | F14: 0 | G14: داخل الخدمة | I14: Factory
A15: 30 | B15: Mohamed Sadek Mohamed Hassanein | C15: محمد صادق محمد حسنين | D15: Miscellaneous Warehouse Section Head | E15: Warehouse (Raw&Pack.) | F15: 0 | G15: داخل الخدمة | I15: Factory
A16: 32 | B16: Ahmed Fathy Ahmed Hassan | C16: احمد فتحى احمد حسن | D16: Solid General Supervisor | E16: Production | F16: 0 | G16: داخل الخدمة | I16: Factory
A17: 33 | B17: Ahmed Mohamed Mohamed Ali | C17: احمد محمد محمد على | D17: Solid General Supervisor | E17: Production | F17: 0 | G17: داخل الخدمة | I17: Factory
A18: 40 | B18: Ahmed Ahmed Mohamed Ahmed Elsandoby | C18: احمد احمد محمد احمد السندوبي | D18: QA systems | E18: Quality Control | F18: 1 | G18: استقالة
A19: 79 | B19: Elsayed Mohamed Elsayed Mohamed | C19: السيد محمد السيد محمد | D19: Line Sales Manager | E19: BU2 | F19: 1 | G19: استقالة | I19: Scientific Office
A20: 154 | B20: Mohamed Ibrahim Mahmoud Elsayed | C20: محمد ابراهيم محمود السيد | D20: Packaging Materials Specialist | E20: Quality Control | F20: 0 | G20: داخل الخدمة | I20: Factory
A21: 165 | B21: Ahmed Fathy Mohamed Mohamed Taha | C21: احمد فتحى محمد محمد طه عبد العال | D21: Warehouse Assistant Technician | E21: Warehouse (Raw&Pack.) | F21: 0 | G21: داخل الخدمة | I21: Factory
A22: 166 | B22: Maher Ibrahim Amry Mohamed | C22: ماهر ابراهيم عمرى محمد | D22: Services Supervisor | E22: Production | F22: 0 | G22: داخل الخدمة | I22: Factory
A23: 167 | B23: Mohamed Elsayed Mohamady Elsayed | C23: محمد السيد محمدى السيد | D23: Services Technician | E23: Engineering | F23: 0 | G23: داخل الخدمة | I23: Factory
A24: 174 | B24: Mohamed Adel Mohamdy elSayed | C24: محمد عادل محمدى السيد عياد | D24: Forklift Operator | E24: Warehouse Finished Product | F24: 0 | G24: داخل الخدمة | I24: Factory
A25: 177 | B25: Amer Ibrahim Abdelaziz | C25: عامر ابراهيم عبد العزيز درويش | D25: Packaging Materials Section Head | E25: Quality Control | F25: 0 | G25: داخل الخدمة | H25: qc1@future-eg.com | I25: Factory
A26: 178 | B26: Ehab Fouad Gerges | C26: ايهاب فؤاد جرجس ميخائيل | D26: Supportive Functions Head | E26: Supportive Functions | F26: 0 | G26: داخل الخدمة | H26: e.fouad@future-eg.com | I26: Scientific Office
A27: 201 | B27: Ayat Mohamed Ibrahim Hanafy | C27: ايات محمد ابراهيم حنفى | D27: QA systems | E27: Production | F27: 1 | G27: استقالة
A28: 207 | B28: Amany Farouk Hassan Youseef | C28: امانى فاروق حسن يوسف | D28: Sales Administration Manager | E28: Sales Administration | F28: 0 | G28: داخل الخدمة | H28: a.hassan@future-eg.com | I28: Scientific Office
A29: 209 | B29: Sanaa Halim Gad el Sayed | C29: سناء حليم جاد السيد | D29: Packaging hall supervisor | E29: Production | F29: 1 | G29: استقالة
A30: 210 | B30: Ahmed ElMoatazBellah Emam | C30: احمد المعتز بالله امام محمد امام الشريف | D30: Production Manager | E30: Production | F30: 1 | G30: استقالة | I30: Factory
A31: 212 | B31: Nabil Noshey Tafeed Shafik | C31: نبيل نصحى تفيد شفيق | D31: Office Boy | E31: Sales Administration | F31: 0 | G31: داخل الخدمة | I31: Sales
A32: 213 | B32: Ahmed Mohamed Ahmed Ebeid | C32: احمد محمد احمد عبيد | D32: Office Boy | E32: Sales Administration | F32: 0 | G32: داخل الخدمة | I32: Sales
A33: 215 | B33: Samy AbdelRazek Mohamed Hussien | C33: سامى عبد الرازق محمد حسين | D33: QC Services Worker | E33: Quality Control | F33: 0 | G33: داخل الخدمة | I33: Factory
A34: 226 | B34: Ragab Abullah Fahmy Hassan | C34: رجب عبد الله فهمى حسن | D34: Gardener | E34: Security | F34: 0 | G34: داخل الخدمة | I34: Factory
A35: 231 | B35: Samar Fahmy Mahmoud Hamed Gwaeed | C35: سمر فهمى محمود حمد جويد | D35: Administration Supervisor | E35: Sales Administration | F35: 0 | G35: داخل الخدمة | I35: Sales
A36: 235 | B36: Salwa Gad Elrab Gad Girgis | C36: سلوى جاد الرب جاد جرجس | D36: Packaging Line Supervisor | E36: Production | F36: 0 | G36: داخل الخدمة | I36: Factory
A37: 238 | B37: Hassan Abu Atteya Hassan Sakr | C37: حسن ابو عطية حسن صقر | D37: A/R Section Head | E37: Finance | F37: 0 | G37: داخل الخدمة | H37: h.sakr@future-eg.com | I37: Factory
A38: 242 | B38: Reda Mazouz Aziz | C38: رضا معزوز عزيز | D38: Production Preparations Technician | E38: Production | F38: 1 | G38: استقالة
A39: 243 | B39: Mohamed Metemed Hendawy Ibrahim | C39: محمد معتمد هنداوى ابراهيم | D39: Solid General Supervisor | E39: Production | F39: 0 | G39: داخل الخدمة | I39: Factory
A40: 245 | B40: Mohmed Khairy Elgendy Mohamed AboAmmer | C40: محمد خيري الجنيدي محمد أبو عامر | D40: Methodology Section Head | E40: R&D | F40: 0 | G40: داخل الخدمة | H40: Methodology@future-eg.com | I40: Factory
A41: 262 | B41: Mohamed Mansour Emam Mostafa | C41: محمد منصور امام مصطفى | D41: Services Supervisor | E41: Warehouse (Raw&Pack.) | F41: 0 | G41: داخل الخدمة | I41: Factory
A42: 268 | B42: Mohamed Zakareya Mohamed Ismaiel | C42: محمد زكريا محمد اسماعيل | D42: Security Manager | E42: Security | F42: 1 | G42: استقالة
A43: 269 | B43: Salwa ElSayed Ahmed Elsayed | C43: سلوي السيد احمد السيد بدوي | D43: Documentation/JDE System Supervisor | E43: Quality Assurance | F43: 1 | G43: استقالة | I43: Factory
A44: 271 | B44: Ahmed Abd El Hakim El Sayed Allam | C44: احمد عبد الحكيم السيد علام | D44: Cafeteria Supervisor | E44: Admin | F44: 1 | G44: استقالة
A45: 272 | B45: Ahmed Ahmed Saeed Mohamed Saeed | C45: احمد احمد سعيد محمد سعيد | D45: Security officer | E45: Security | F45: 1 | G45: استقالة
A46: 276 | B46: Islam Mohamed Essa Ramadam ElSharkawy | C46: اسلام محمد عيسى رمضان الشرقاوى | D46: QC Manager | E46: Quality Control | F46: 0 | G46: داخل الخدمة | H46: i.sharkawy@future-eg.com | I46: Factory
A47: 278 | B47: Mohamed Magdy Khalil | C47: محمد مجدي خليل | D47: Procurement Specialist | E47: Marketing | F47: 1 | G47: استقالة
A48: 279 | B48: Mohamed Hatem Abdou Mohamed Abdou | C48: محمد حاتم عبده محمد عبده | D48: Engineering Department Manager | E48: Engineering | F48: 0 | G48: داخل الخدمة | I48: Factory
A49: 280 | B49: Ahmed Mahmoud Mahmoud ElMelegy | C49: احمد محمود محمود المليجى | D49: National Sales Manager | E49: Sales Management | F49: 0 | G49: داخل الخدمة | I49: Scientific Office
A50: 281 | B50: Ashraf Amgad Faragalla Abdelmalak | C50: اشرف امجد فرج الله عبد الملاك | D50: Scientific Office General Manager | E50: Sales Management | F50: 0 | G50: داخل الخدمة | H50: a.faragalla@future-eg.com | I50: Scientific Office
A51: 297 | B51: Mahmoud Mohamed Mahmoud Youssef | C51: محمود محمد محمود يوسف | D51: Senior Medical Representative | E51: BU2 | F51: 1 | G51: استقالة
A52: 306 | B52: Hassan Ahmed Nasser Ahmed | C52: حسن احمد نصر احمد | D52: Senior Medical Representative | E52: BU1 | F52: 0 | G52: داخل الخدمة | I52: Sales
A53: 309 | B53: Ahmed AbelNour Mohamed Emam ElGazar | C53: احمد ابو النور محمد امام الجزايرى | D53: Acting as Field Force Supervisor | E53: BU5 | F53: 0 | G53: داخل الخدمة | I53: Sales
A54: 326 | B54: Mousa Abdelwahab Mousa | C54: موسى عبد الوهاب موسى شلبى | D54: Raw Materials Supervisor | E54: Warehouse (Raw&Pack.) | F54: 0 | G54: داخل الخدمة | I54: Factory
A55: 330 | B55: Mahmoud Kheir El Gamal Khalil | C55: محمود خير الجمل خليل | D55: Senior Medical Representative | E55: BU1 | F55: 1 | G55: استقالة
A56: 335 | B56: Ahmed Hefny Shehata Aly | C56: احمد حفنى شحاتة على | D56: Acting As Area Sales Manager | E56: BU1 | F56: 1 | G56: استقالة
A57: 336 | B57: Adel Asaad Gad ElSayed | C57: عادل أسعد جاد السيد | D57: Area Sales Manager | E57: BU2 | F57: 1 | G57: استقالة | I57: Sales
A58: 337 | B58: Ester Samir Boshra | C58: إستر سمير بشرى | D58: Senior Medical Representative | E58: BU1 | F58: 1 | G58: استقالة
A59: 342 | B59: Tamer Sayed Mohamed Ahmed AlGhazaly | C59: تامر سيد محمد احمد الغزالى | D59: Electrical Technician | E59: Engineering | F59: 0 | G59: داخل الخدمة | I59: Factory
A60: 355 | B60: Mohamed Ramadan AbdelBaset AbdelGhany | C60: محمد رمضان عبد الباسط عبد الغني | D60: District Sales Manager | E60: BU5 | F60: 1 | G60: استقالة | I60: Sales
A61: 378 | B61: Niveen Mahfouz Fekry AbdelMalak | C61: نيفين محفوظ فكرى عبد الملاك | D61: Senior Medical Representative | E61: BU2 | F61: 0 | G61: داخل الخدمة | I61: Sales
A62: 382 | B62: Emad Ali Hassan abu elsoaud | C62: عماد علي حسن أبو السعود | D62: Security Supervisor | E62: Security | F62: 1 | G62: استقالة
A63: 383 | B63: Mohamed AbdelRazek Mohamed Morsy Soliman | C63: محمد عبد الرازق محمد مرسى سليمان | D63: Security Supervisor | E63: Security | F63: 0 | G63: داخل الخدمة | I63: Factory
A64: 390 | B64: Ghada AbdAllah AlSherif | C64: غادة عبد الله محمد احمد الشريف | D64: CHRO | E64: H.R | F64: 0 | G64: داخل الخدمة | H64: galsherif@future-eg.com | I64: Scientific Office
A65: 391 | B65: Adel Mousa Gerges | C65: عادل موسى جرجس تادرس | D65: Social Insurance Consultant | E65: H.R | F65: 1 | G65: استقالة | I65: Scientific Office
A66: 397 | B66: Marian Hanna Labib | C66: ماريان حنا لبيب | D66: Senior Medical Representative | E66: BU1 | F66: 1 | G66: استقالة
A67: 398 | B67: Mina Mikhael Adeeb Ibrahim Fahmy | C67: مينا ميخائيل اديب ابراهيم فهمى | D67: Acting As Area Sales Manager | E67: BU5 | F67: 1 | G67: استقالة
A68: 403 | B68: Emad Moawad Eid Mansour | C68: عماد معوض عيد منصور | D68: Area Sales Manager | E68: BU1 | F68: 0 | G68: داخل الخدمة | I68: Sales
A69: 404 | B69: DiaaelDin ElSaid AbdelAtti Afify | C69: ضياء الدين السيد عبد العاطى عفيفى | D69: Area Sales Manager | E69: BU5 | F69: 0 | G69: داخل الخدمة | I69: Sales
A70: 405 | B70: Neermen Gouda Elsayed Kaff | C70: نيرمين جودة السيد كف | D70: District Sales Manager | E70: BU1 | F70: 0 | G70: داخل الخدمة | I70: Sales
A71: 413 | B71: Soliman Ibrahim Soliman Zaid | C71: سليمان ابراهيم سليمان ابراهيم زيد | D71: Laboratory Store Keeper | E71: Quality Control | F71: 0 | G71: داخل الخدمة | I71: Factory
A72: 426 | B72: Mohamed Ahmed Abd El Haliem Ahmed | C72: محمد احمد عبد الحليم احمد | D72: SFE Section Head | E72: Supportive Functions | F72: 1 | G72: استقالة
A73: 436 | B73: Shady Abu ElYazed AbdelMoneim ElAhmar | C73: شادي ابو اليزيد عبد المنعم الاحمر | D73: Senior Medical Representative | E73: BU1 | F73: 1 | G73: استقالة
A74: 438 | B74: Hoda Hassan Mohamed Mostafa Mattar | C74: هدى حسن محمد مصطفى مطر | D74: Packaging Line Supervisor | E74: Production | F74: 0 | G74: داخل الخدمة | I74: Factory
A75: 439 | B75: Taha Salah Salem Morsy | C75: طه صلاح سالم مرسي | D75: Coating Line Leader | E75: Production | F75: 1 | G75: استقالة
A76: 441 | B76: Yousef Wageh Ebrahim Ali | C76: يوسف وجيه ابراهيم علي | D76: QA systems | E76: Production | F76: 1 | G76: استقالة
A77: 448 | B77: Micheal Roshdy Attia Rizk Farag | C77: مايكل رشدى عطية رزق فرج | D77: Area Sales Manager | E77: BU5 | F77: 0 | G77: داخل الخدمة | I77: Sales
A78: 454 | B78: Islam Samy Houssny hassanien | C78: إسلام سامي حسني حسنين | D78: Driver | E78: Transportation | F78: 1 | G78: استقالة
A79: 461 | B79: Abd El-Aziz Mohamed ElZanaty Mohamed | C79: عبد العزيز محمد الزناتي محمد | D79: Senior Medical Representative | E79: BU2 | F79: 1 | G79: استقالة
A80: 462 | B80: Raouth Shehata Abd El Malak | C80: رعوث شحاتة عبد الملك | D80: Senior Medical Representative | E80: BU1 | F80: 1 | G80: استقالة
A81: 466 | B81: Wael Abdel samiea Mostafa | C81: وائل عبد السميع مصطفى | D81: Business Unit Manager | E81: BU4 | F81: 1 | G81: استقالة
A82: 475 | B82: Maged Gaber Nazeem Saad | C82: ماجد جابر نظيم سعد | D82: Area Sales Manager | E82: BU4 | F82: 1 | G82: استقالة
A83: 480 | B83: AbdelRahim Ahmed Abbas Ahmed | C83: عبد الرحيم احمد عباس احمد | D83: Senior Product Specialist | E83: BU4 | F83: 1 | G83: استقالة
A84: 482 | B84: Sedrak William Yousef Gerges | C84: سدراك وليم يوسف جرجس | D84: Senior District Manager | E84: BU3 | F84: 1 | G84: استقالة
A85: 485 | B85: Mina Gamal Hakim Issa | C85: مينا جمال حكيم عيسى | D85: Senior Product Specialist | E85: BU4 | F85: 1 | G85: استقالة | I85: Sales
A86: 486 | B86: Mohamed Fathy Abd El Salam Tawfik | C86: محمد فتحي عبد السلام توفيق | D86: Product Specialist | E86: BU4 | F86: 1 | G86: استقالة
A87: 488 | B87: Mohamed raouf saeed | C87: محمد رؤوف سعيد | D87: HR Section Head | E87: H.R | F87: 1 | G87: استقالة
A88: 491 | B88: Mohamed Ragab Emam Abo Elmagd | C88: محمد رجب امام ابو المجد | D88: QA systems | E88: BU3 | F88: 1 | G88: استقالة
A89: 500 | B89: Emad Hamdy AbdelKareem AbdelMaged | C89: عماد حمدى عبد الكريم عبد المجيد | D89: Admin Affairs Deputy Manager | E89: H.R | F89: 0 | G89: داخل الخدمة | H89: e.hamdy@future-eg.com | I89: Factory
A90: 503 | B90: Ahmed Mohamed Nabil Abd El Sameea Mohamed | C90: احمد محمد نبيل عبد السميع محمد | D90: Acting As R&D Manager | E90: R&D | F90: 1 | G90: استقالة
A91: 507 | B91: Nabil Samuel Boctor Botros | C91: نبيل صموئيل بقطر بطرس | D91: Supervisor | E91: BU2 | F91: 1 | G91: استقالة
A92: 517 | B92: Rehab Maged Mohamed ElSaeed Hosny ElTarhouny | C92: رحاب ماجد محمد السعيد حسنى التراهونى | D92: District Sales Manager | E92: BU2 | F92: 0 | G92: داخل الخدمة | I92: Sales
A93: 522 | B93: Marian Farouk Sedky Botros Basta | C93: ماريان فاروق صدقى بطرس بسطا | D93: Field Force Supervisor | E93: BU1 | F93: 1 | G93: استقالة
A94: 530 | B94: Nermeen Hosny Sobhy Zaki | C94: نرمين حسني صبحي زكي | D94: QA systems | E94: BU3 | F94: 1 | G94: استقالة
A95: 531 | B95: Wael Mousa Abdelfatah Attallah | C95: وائل موسى عبد الفتاح عطا الله | D95: National Tender Sales Manager | E95: Supportive Functions | F95: 0 | G95: داخل الخدمة | I95: Scientific Office
A96: 537 | B96: Ahmed Ezzat Ali Mahdy | C96: احمد عزت على مهدى | D96: Field Force Supervisor | E96: BU3 | F96: 0 | G96: داخل الخدمة | I96: Sales
A97: 548 | B97: Eslam Ahmed AbdelHakeem Mostafa | C97: اسلام احمد عبد الحكيم مصطفى | D97: Stability Section Head | E97: Quality Control | F97: 1 | G97: استقالة | I97: Factory
A98: 552 | B98: Ahmed Attia Sabry AbdelRahman | C98: احمد عطية صبرى عبد الرحمن | D98: R&D Document Control Supervisor | E98: R&D | F98: 0 | G98: داخل الخدمة | I98: Factory
A99: 559 | B99: Ahmed Mohamed Rashiq Hassan | C99: احمد محمد رشيق حسن | D99: Product Specialist | E99: BU4 | F99: 1 | G99: استقالة
A100: 560 | B100: Amr Ezzat Abd El-Ghafar | C100: عمرو عزت عبد الغفار | D100: Methodology Section Head | E100: R&D | F100: 1 | G100: استقالة
...
